<?xml version="1.0" encoding="UTF-8"?>
<checkstyle version="5.0">
 <file name="/home/ivan/IdeaProjects/firelib/ibadapter/src/main/scala/firelib/ibadapter/IbTradeGate.scala">
  <error line="1" source="org.scalastyle.file.HeaderMatchesChecker" severity="warning" message="Header does not match expected text"></error>
  <error line="140" source="org.scalastyle.file.FileLineLengthChecker" severity="warning" message="File line length exceeds 160 characters"></error>
  <error line="166" source="org.scalastyle.file.FileLineLengthChecker" severity="warning" message="File line length exceeds 160 characters"></error>
  <error line="167" source="org.scalastyle.file.FileLineLengthChecker" severity="warning" message="File line length exceeds 160 characters"></error>
  <error line="168" source="org.scalastyle.file.FileLineLengthChecker" severity="warning" message="File line length exceeds 160 characters"></error>
  <error line="170" source="org.scalastyle.file.FileLineLengthChecker" severity="warning" message="File line length exceeds 160 characters"></error>
  <error line="171" source="org.scalastyle.file.FileLineLengthChecker" severity="warning" message="File line length exceeds 160 characters"></error>
  <error line="173" source="org.scalastyle.file.FileLineLengthChecker" severity="warning" message="File line length exceeds 160 characters"></error>
  <error column="17" line="147" source="org.scalastyle.scalariform.ParameterNumberChecker" severity="warning" message="The number of parameters should not exceed 8"></error>
  <error column="38" line="46" source="org.scalastyle.scalariform.MagicNumberChecker" severity="warning" message="Magic Number"></error>
  <error column="11" line="125" source="org.scalastyle.scalariform.MagicNumberChecker" severity="warning" message="Magic Number"></error>
  <error column="14" line="125" source="org.scalastyle.scalariform.MagicNumberChecker" severity="warning" message="Magic Number"></error>
  <error column="35" line="44" source="org.scalastyle.scalariform.ReturnChecker" severity="warning" message="Avoid using return"></error>
  <error column="12" line="49" source="org.scalastyle.scalariform.ReturnChecker" severity="warning" message="Avoid using return"></error>
  <error column="8" line="51" source="org.scalastyle.scalariform.ReturnChecker" severity="warning" message="Avoid using return"></error>
  <error column="16" line="161" source="org.scalastyle.scalariform.ReturnChecker" severity="warning" message="Avoid using return"></error>
  <error column="8" line="213" source="org.scalastyle.scalariform.ReturnChecker" severity="warning" message="Avoid using return"></error>
  <error column="12" line="218" source="org.scalastyle.scalariform.ReturnChecker" severity="warning" message="Avoid using return"></error>
  <error column="8" line="232" source="org.scalastyle.scalariform.ReturnChecker" severity="warning" message="Avoid using return"></error>
  <error column="8" line="283" source="org.scalastyle.scalariform.ReturnChecker" severity="warning" message="Avoid using return"></error>
  <error column="21" line="47" source="org.scalastyle.scalariform.NullChecker" severity="warning" message="Avoid using null"></error>
  <error column="8" line="92" source="org.scalastyle.scalariform.PublicMethodsHaveTypeChecker" severity="warning" message="Public method must have explicit type"></error>
  <error column="8" line="94" source="org.scalastyle.scalariform.PublicMethodsHaveTypeChecker" severity="warning" message="Public method must have explicit type"></error>
  <error column="8" line="122" source="org.scalastyle.scalariform.PublicMethodsHaveTypeChecker" severity="warning" message="Public method must have explicit type"></error>
  <error column="17" line="133" source="org.scalastyle.scalariform.PublicMethodsHaveTypeChecker" severity="warning" message="Public method must have explicit type"></error>
  <error column="17" line="193" source="org.scalastyle.scalariform.PublicMethodsHaveTypeChecker" severity="warning" message="Public method must have explicit type"></error>
  <error column="17" line="239" source="org.scalastyle.scalariform.PublicMethodsHaveTypeChecker" severity="warning" message="Public method must have explicit type"></error>
  <error column="17" line="248" source="org.scalastyle.scalariform.PublicMethodsHaveTypeChecker" severity="warning" message="Public method must have explicit type"></error>
  <error column="12" line="269" source="org.scalastyle.scalariform.PublicMethodsHaveTypeChecker" severity="warning" message="Public method must have explicit type"></error>
  <error column="0" line="9" source="org.scalastyle.scalariform.UnderscoreImportChecker" severity="warning" message="Avoid wildcard imports"></error>
 </file>
</checkstyle>
